oneloop_client/__init__.py
oneloop_client/api_client.py
oneloop_client/api_response.py
oneloop_client/configuration.py
oneloop_client/exceptions.py
oneloop_client/py.typed
oneloop_client/rest.py
oneloop_client/api/__init__.py
oneloop_client/api/default_api.py
oneloop_client/models/__init__.py
oneloop_client/models/api_key.py
oneloop_client/models/api_key_scope.py
oneloop_client/models/create_api_key_request.py
oneloop_client/models/create_api_key_response.py
oneloop_client/models/create_api_key_response_api_key.py
oneloop_client/models/create_workspace_request.py
oneloop_client/models/create_workspace_response.py
oneloop_client/models/create_workspace_scope_request.py
oneloop_client/models/create_workspace_scope_response.py
oneloop_client/models/delete_api_key_response.py
oneloop_client/models/error_response.py
oneloop_client/models/error_response_error.py
oneloop_client/models/refill_api_key_request.py
oneloop_client/models/refill_api_key_response.py
oneloop_client/models/retrieve_all_workspace_scopes_response.py
oneloop_client/models/retrieve_api_key_by_id_response.py
oneloop_client/models/retrieve_api_keys_response.py
oneloop_client/models/retrieve_workspace_by_id_response.py
oneloop_client/models/retrieve_workspace_response.py
oneloop_client/models/rotate_api_key_response.py
oneloop_client/models/update_workspace_response.py
oneloop_client/models/verify_api_key_request.py
oneloop_client/models/verify_api_key_response.py
oneloop_client/models/workspace.py
oneloop_client/models/workspace_scope.py
oneloop_python-0.0.1.dist-info/METADATA
oneloop_python-0.0.1.dist-info/WHEEL
oneloop_python-0.0.1.dist-info/top_level.txt
oneloop_python-0.0.1.dist-info/RECORD
